odoo/addons/product_contract_date_end_unrequired/__init__.py
odoo/addons/product_contract_date_end_unrequired/__manifest__.py
odoo/addons/product_contract_date_end_unrequired/models/__init__.py
odoo/addons/product_contract_date_end_unrequired/models/crm_lead.py
odoo/addons/product_contract_date_end_unrequired/models/crm_sale_order_line.py
odoo/addons/product_contract_date_end_unrequired/security/ir.model.access.csv
odoo/addons/product_contract_date_end_unrequired/views/sale_order.xml
odoo12_addon_product_contract_date_end_unrequired-12.0.0.1.0.dist-info/METADATA
odoo12_addon_product_contract_date_end_unrequired-12.0.0.1.0.dist-info/WHEEL
odoo12_addon_product_contract_date_end_unrequired-12.0.0.1.0.dist-info/top_level.txt
odoo12_addon_product_contract_date_end_unrequired-12.0.0.1.0.dist-info/RECORD
